Metadata-Version: 2.4
Name: sevenn
Version: 0.12.0
Summary: Scalable EquiVariance Enabled Neural Network
Author: Jaesun Kim, Gijin Kim, Hyungmin An
Author-email: Yutack Park <parkyutack@snu.ac.kr>, Haekwan Jeon <haekwan98@snu.ac.kr>
License: MIT License
Project-URL: Homepage, https://github.com/MDIL-SNU/SevenNet
Project-URL: Issues, https://github.com/MDIL-SNU/SevenNet/issues
Classifier: Programming Language :: Python :: 3
Classifier: License :: OSI Approved :: MIT License
Classifier: Operating System :: POSIX :: Linux
Requires-Python: >=3.8
License-File: LICENSE
Requires-Dist: ase
Requires-Dist: braceexpand
Requires-Dist: pyyaml
Requires-Dist: e3nn>=0.5.0
Requires-Dist: tqdm
Requires-Dist: scikit-learn
Requires-Dist: torch_geometric>=2.5.0
Requires-Dist: numpy
Requires-Dist: matscipy
Requires-Dist: pandas
Requires-Dist: requests
Requires-Dist: ninja
Requires-Dist: setuptools>=61.0
Provides-Extra: test
Requires-Dist: pytest; extra == "test"
Requires-Dist: pytest-cov>=5; extra == "test"
Requires-Dist: ipython; extra == "test"
Provides-Extra: cueq12
Requires-Dist: cuequivariance>=0.6.0; python_version >= "3.10" and extra == "cueq12"
Requires-Dist: cuequivariance-torch>=0.6.0; python_version >= "3.10" and extra == "cueq12"
Requires-Dist: cuequivariance-ops-torch-cu12; python_version >= "3.10" and extra == "cueq12"
Provides-Extra: mliap
Requires-Dist: cython==3.0.11; extra == "mliap"
Requires-Dist: cupy-cuda12x; extra == "mliap"
Dynamic: license-file
